steamuck/__init__.py
steamuck-1.0.0.dist-info/METADATA
steamuck-1.0.0.dist-info/WHEEL
steamuck-1.0.0.dist-info/top_level.txt
steamuck-1.0.0.dist-info/RECORD
