Metadata-Version: 2.1
Name: steamuck
Version: 1.0.0
Summary: A support library for creating plugins with Steamuck.
Home-page: https://github.com/Steamuck/SDK
Author: Steamuck Team
Classifier: Intended Audience :: Developers
Classifier: License :: OSI Approved :: GNU General Public License v3 (GPLv3)
Classifier: Programming Language :: Python :: 3.11
Requires-Python: >=3.11.8
